solentware_grid/__init__.py
solentware_grid/datagrid.py
solentware_grid/core/__init__.py
solentware_grid/core/dataclient.py
solentware_grid/core/dataregister.py
solentware_grid/core/datasourcecursor.py
solentware_grid/core/nulldatasource.py
solentware_grid/gui/__init__.py
solentware_grid/gui/callbackexception.py
solentware_grid/gui/constants.py
solentware_grid/gui/datadelete.py
solentware_grid/gui/dataedit.py
solentware_grid/gui/datarow.py
solentware_grid/gui/datashow.py
solentware_grid/gui/eventspec.py
solentware_grid/gui/gridbindings.py
solentware_grid-3.0.1.dist-info/LICENCE
solentware_grid-3.0.1.dist-info/METADATA
solentware_grid-3.0.1.dist-info/WHEEL
solentware_grid-3.0.1.dist-info/top_level.txt
solentware_grid-3.0.1.dist-info/RECORD
