Metadata-Version: 2.1
Name: solentware-grid
Version: 3.0.1
Summary: Database display classes.
Author-email: Roger Marsh <roger.marsh@solentware.co.uk>
License: Licence for solentware_grid package
Project-URL: Homepage, http://www.solentware.co.uk
Project-URL: Repository, https://github.com/RogerMarsh/solentware-grid.git
Project-URL: Bug Tracker, https://github.com/RogerMarsh/solentware-grid/issues
Classifier: License :: OSI Approved :: BSD License
Classifier: Programming Language :: Python :: 3.10
Classifier: Programming Language :: Python :: 3.11
Classifier: Programming Language :: Python :: 3.12
Classifier: Operating System :: OS Independent
Classifier: Topic :: Software Development
Classifier: Intended Audience :: Developers
Classifier: Development Status :: 3 - Alpha
License-File: LICENCE
Requires-Dist: solentware-bind==1.0.2
